CHANGELOG.txt
LICENCE.txt
MANIFEST.in
README.txt
setup.py
akshatprime/__init__.py
akshatprime.egg-info/PKG-INFO
akshatprime.egg-info/SOURCES.txt
akshatprime.egg-info/dependency_links.txt
akshatprime.egg-info/top_level.txt