Metadata-Version: 2.4
Name: akshatprime
Version: 0.0.1
Summary: Identifying a prime number
Home-page: 
Author: Akshat Gupta
Author-email: akshatg@iitbhilai.ac.in
License: MIT
Keywords: prime
Classifier: Development Status :: 5 - Production/Stable
Classifier: Intended Audience :: Education
Classifier: Operating System :: OS Independent
Classifier: License :: OSI Approved :: MIT License
Classifier: Programming Language :: Python :: 3
License-File: LICENCE.txt
Dynamic: author
Dynamic: author-email
Dynamic: classifier
Dynamic: description
Dynamic: keywords
Dynamic: license
Dynamic: license-file
Dynamic: summary
